{
  "2": {
    "id": 2,
    "order": "2.00000000000000000000",
    "name": [
      {
        "id": 2,
        "value": "BNF, Latin 14426"
      }
    ],
    "jad_id": "jad_manuscript__2",
    "library": [
      {
        "id": 2,
        "value": "Bibliothèque Nationale de France",
        "order": "2.00000000000000000000"
      }
    ],
    "idno": "Latin 14426",
    "catalog_url": "https://archivesetmanuscrits.bnf.fr/ark:/12148/cc75180c",
    "digi_url": "https://gallica.bnf.fr/ark:/12148/btv1b9078089g",
    "institutional_context": [
      {
        "id": 1,
        "value": "University of Paris",
        "order": "1.00000000000000000000"
      }
    ],
    "date_written": [
      {
        "id": 41,
        "value": "13th cen.",
        "order": "41.00000000000000000000"
      }
    ],
    "Format (Höhe x Breite / Anzahl folios)": null,
    "library_abb": [
      {
        "id": 2,
        "value": "BNF"
      }
    ]
  },
  "3": {
    "id": 3,
    "order": "3.00000000000000000000",
    "name": [
      {
        "id": 3,
        "value": "San Isidoro, MS 11"
      }
    ],
    "jad_id": "jad_manuscript__3",
    "library": [
      {
        "id": 3,
        "value": "San Isidoro (Kloster)",
        "order": "3.00000000000000000000"
      }
    ],
    "idno": "MS 11",
    "catalog_url": "",
    "digi_url": "",
    "institutional_context": [
      {
        "id": 7,
        "value": "Augustinian canons León",
        "order": "7.00000000000000000000"
      }
    ],
    "date_written": [
      {
        "id": 42,
        "value": "1197-1203",
        "order": "42.00000000000000000000"
      }
    ],
    "Format (Höhe x Breite / Anzahl folios)": null,
    "library_abb": [
      {
        "id": 3,
        "value": "San Isidoro"
      }
    ]
  },
  "4": {
    "id": 4,
    "order": "4.00000000000000000000",
    "name": [
      {
        "id": 2,
        "value": "BNF, Latin 8865"
      }
    ],
    "jad_id": "jad_manuscript__4",
    "library": [
      {
        "id": 2,
        "value": "Bibliothèque Nationale de France",
        "order": "2.00000000000000000000"
      }
    ],
    "idno": "Latin 8865",
    "catalog_url": "https://archivesetmanuscrits.bnf.fr/ark:/12148/cc623934",
    "digi_url": "https://gallica.bnf.fr/ark:/12148/btv1b6000541b",
    "institutional_context": [],
    "date_written": [],
    "Format (Höhe x Breite / Anzahl folios)": null,
    "library_abb": [
      {
        "id": 2,
        "value": "BNF"
      }
    ]
  },
  "5": {
    "id": 5,
    "order": "5.00000000000000000000",
    "name": [
      {
        "id": 4,
        "value": "St.Gen., MS 1423"
      }
    ],
    "jad_id": "jad_manuscript__5",
    "library": [
      {
        "id": 4,
        "value": "Bibliothèque Sainte-Geneviève",
        "order": "4.00000000000000000000"
      }
    ],
    "idno": "MS 1423",
    "catalog_url": "https://calames.abes.fr/pub/bsg.aspx#details?id=BSGB10400",
    "digi_url": "",
    "institutional_context": [
      {
        "id": 1,
        "value": "University of Paris",
        "order": "1.00000000000000000000"
      }
    ],
    "date_written": [
      {
        "id": 5,
        "value": "late 12th cen.",
        "order": "5.00000000000000000000"
      }
    ],
    "Format (Höhe x Breite / Anzahl folios)": null,
    "library_abb": [
      {
        "id": 4,
        "value": "St.Gen."
      }
    ]
  },
  "6": {
    "id": 6,
    "order": "6.00000000000000000000",
    "name": [
      {
        "id": 2,
        "value": "BNF, Latin 492"
      }
    ],
    "jad_id": "jad_manuscript__6",
    "library": [
      {
        "id": 2,
        "value": "Bibliothèque Nationale de France",
        "order": "2.00000000000000000000"
      }
    ],
    "idno": "Latin 492",
    "catalog_url": "https://archivesetmanuscrits.bnf.fr/ark:/12148/cc619341",
    "digi_url": "",
    "institutional_context": [
      {
        "id": 1,
        "value": "University of Paris",
        "order": "1.00000000000000000000"
      }
    ],
    "date_written": [
      {
        "id": 41,
        "value": "13th cen.",
        "order": "41.00000000000000000000"
      }
    ],
    "Format (Höhe x Breite / Anzahl folios)": "31 x 21, 117 ff.",
    "library_abb": [
      {
        "id": 2,
        "value": "BNF"
      }
    ]
  },
  "7": {
    "id": 7,
    "order": "7.00000000000000000000",
    "name": [
      {
        "id": 5,
        "value": "Maz., MS 177"
      }
    ],
    "jad_id": "jad_manuscript__7",
    "library": [
      {
        "id": 5,
        "value": "Bibliothèque Mazarine",
        "order": "5.00000000000000000000"
      }
    ],
    "idno": "MS 177",
    "catalog_url": "https://calames.abes.fr/pub/mazarine.aspx#details?id=MAZA10313",
    "digi_url": "https://bibnum.institutdefrance.fr/records/item/17954-commentaires-sur-une-partie-de-la-bible",
    "institutional_context": [
      {
        "id": 1,
        "value": "University of Paris",
        "order": "1.00000000000000000000"
      }
    ],
    "date_written": [
      {
        "id": 41,
        "value": "13th cen.",
        "order": "41.00000000000000000000"
      }
    ],
    "Format (Höhe x Breite / Anzahl folios)": "27 x 21, 199 ff.",
    "library_abb": [
      {
        "id": 5,
        "value": "Maz."
      }
    ]
  },
  "8": {
    "id": 8,
    "order": "8.00000000000000000000",
    "name": [
      {
        "id": 4,
        "value": "St.Gen., MS 1422"
      }
    ],
    "jad_id": "jad_manuscript__8",
    "library": [
      {
        "id": 4,
        "value": "Bibliothèque Sainte-Geneviève",
        "order": "4.00000000000000000000"
      }
    ],
    "idno": "MS 1422",
    "catalog_url": "https://calames.abes.fr/pub/bsg.aspx#details?id=BSGB10393",
    "digi_url": "",
    "institutional_context": [],
    "date_written": [
      {
        "id": 41,
        "value": "13th cen.",
        "order": "41.00000000000000000000"
      }
    ],
    "Format (Höhe x Breite / Anzahl folios)": null,
    "library_abb": [
      {
        "id": 4,
        "value": "St.Gen."
      }
    ]
  },
  "9": {
    "id": 9,
    "order": "9.00000000000000000000",
    "name": [
      {
        "id": 6,
        "value": "Lam., MS 144"
      }
    ],
    "jad_id": "jad_manuscript__9",
    "library": [
      {
        "id": 6,
        "value": "Lambeth Palace Library",
        "order": "6.00000000000000000000"
      }
    ],
    "idno": "MS 144",
    "catalog_url": "https://archives.lambethpalacelibrary.org.uk/CalmView/Record.aspx?src=CalmView.Catalog&id=MSS%2f144&pos=1",
    "digi_url": "",
    "institutional_context": [
      {
        "id": 6,
        "value": "See of Canterbury",
        "order": "6.00000000000000000000"
      }
    ],
    "date_written": [
      {
        "id": 9,
        "value": "around 1200",
        "order": "9.00000000000000000000"
      },
      {
        "id": 11,
        "value": "after 1187",
        "order": "11.00000000000000000000"
      }
    ],
    "Format (Höhe x Breite / Anzahl folios)": null,
    "library_abb": [
      {
        "id": 6,
        "value": "Lam."
      }
    ]
  },
  "10": {
    "id": 10,
    "order": "10.00000000000000000000",
    "name": [
      {
        "id": 2,
        "value": "BNF, Latin 446"
      }
    ],
    "jad_id": "jad_manuscript__10",
    "library": [
      {
        "id": 2,
        "value": "Bibliothèque Nationale de France",
        "order": "2.00000000000000000000"
      }
    ],
    "idno": "Latin 446",
    "catalog_url": "https://archivesetmanuscrits.bnf.fr/ark:/12148/cc618815",
    "digi_url": "https://gallica.bnf.fr/ark:/12148/btv1b10721053z/f213.item",
    "institutional_context": [],
    "date_written": [
      {
        "id": 9,
        "value": "around 1200",
        "order": "9.00000000000000000000"
      }
    ],
    "Format (Höhe x Breite / Anzahl folios)": "25 x 17, 214 ff.",
    "library_abb": [
      {
        "id": 2,
        "value": "BNF"
      }
    ]
  },
  "11": {
    "id": 11,
    "order": "11.00000000000000000000",
    "name": [
      {
        "id": 2,
        "value": "BNF, Latin 3737"
      }
    ],
    "jad_id": "jad_manuscript__11",
    "library": [
      {
        "id": 2,
        "value": "Bibliothèque Nationale de France",
        "order": "2.00000000000000000000"
      }
    ],
    "idno": "Latin 3737",
    "catalog_url": "https://archivesetmanuscrits.bnf.fr/ark:/12148/cc61689r",
    "digi_url": "https://gallica.bnf.fr/ark:/12148/btv1b52502392s/",
    "institutional_context": [],
    "date_written": [
      {
        "id": 17,
        "value": "around 1300",
        "order": "17.00000000000000000000"
      }
    ],
    "Format (Höhe x Breite / Anzahl folios)": null,
    "library_abb": [
      {
        "id": 2,
        "value": "BNF"
      }
    ]
  },
  "12": {
    "id": 12,
    "order": "12.00000000000000000000",
    "name": [
      {
        "id": 4,
        "value": "St.Gen., MS 2787"
      }
    ],
    "jad_id": "jad_manuscript__12",
    "library": [
      {
        "id": 4,
        "value": "Bibliothèque Sainte-Geneviève",
        "order": "4.00000000000000000000"
      }
    ],
    "idno": "MS 2787",
    "catalog_url": "https://calames.abes.fr/pub/bsg.aspx#details?id=BSGC10617",
    "digi_url": "",
    "institutional_context": [
      {
        "id": 1,
        "value": "University of Paris",
        "order": "1.00000000000000000000"
      }
    ],
    "date_written": [
      {
        "id": 20,
        "value": "early 13th cen.",
        "order": "20.00000000000000000000"
      }
    ],
    "Format (Höhe x Breite / Anzahl folios)": "19 x 14, 225 ff.",
    "library_abb": [
      {
        "id": 4,
        "value": "St.Gen."
      }
    ]
  },
  "13": {
    "id": 13,
    "order": "13.00000000000000000000",
    "name": [
      {
        "id": 7,
        "value": "BL, Arundel 322"
      }
    ],
    "jad_id": "jad_manuscript__13",
    "library": [
      {
        "id": 7,
        "value": "British Library",
        "order": "7.00000000000000000000"
      }
    ],
    "idno": "Arundel 322",
    "catalog_url": "",
    "digi_url": "",
    "institutional_context": [],
    "date_written": [],
    "Format (Höhe x Breite / Anzahl folios)": null,
    "library_abb": [
      {
        "id": 7,
        "value": "BL"
      }
    ]
  },
  "14": {
    "id": 14,
    "order": "14.00000000000000000000",
    "name": [
      {
        "id": 7,
        "value": "BL, Royal 8 F XVII"
      }
    ],
    "jad_id": "jad_manuscript__14",
    "library": [
      {
        "id": 7,
        "value": "British Library",
        "order": "7.00000000000000000000"
      }
    ],
    "idno": "Royal 8 F XVII",
    "catalog_url": "",
    "digi_url": "",
    "institutional_context": [],
    "date_written": [],
    "Format (Höhe x Breite / Anzahl folios)": null,
    "library_abb": [
      {
        "id": 7,
        "value": "BL"
      }
    ]
  },
  "15": {
    "id": 15,
    "order": "15.00000000000000000000",
    "name": [
      {
        "id": 2,
        "value": "BNF, Latin 620"
      }
    ],
    "jad_id": "jad_manuscript__15",
    "library": [
      {
        "id": 2,
        "value": "Bibliothèque Nationale de France",
        "order": "2.00000000000000000000"
      }
    ],
    "idno": "Latin 620",
    "catalog_url": "https://archivesetmanuscrits.bnf.fr/ark:/12148/cc62076x",
    "digi_url": "https://gallica.bnf.fr/ark:/12148/btv1b10036602t",
    "institutional_context": [
      {
        "id": 1,
        "value": "University of Paris",
        "order": "1.00000000000000000000"
      }
    ],
    "date_written": [],
    "Format (Höhe x Breite / Anzahl folios)": null,
    "library_abb": [
      {
        "id": 2,
        "value": "BNF"
      }
    ]
  },
  "16": {
    "id": 16,
    "order": "16.00000000000000000000",
    "name": [
      {
        "id": 1,
        "value": "ÖNB, Cod. 1014"
      }
    ],
    "jad_id": "jad_manuscript__16",
    "library": [
      {
        "id": 1,
        "value": "Österreichische Nationalbibliothek",
        "order": "1.00000000000000000000"
      }
    ],
    "idno": "Cod. 1014",
    "catalog_url": "https://search.onb.ac.at/primo-explore/fulldisplay?docid=ONB_alma21302484910003338&context=L&vid=ONB&lang=de_DE&search_scope=ONB_gesamtbestand&adaptor=Local%20Search%20Engine&tab=default_tab&query=any,contains,cod.%201014&mode=basic",
    "digi_url": "https://digital.onb.ac.at/RepViewer/viewer.faces?doc=DTL_8518292&order=1&view=SINGLE",
    "institutional_context": [
      {
        "id": 20,
        "value": "Benedictines Mondsee",
        "order": "20.00000000000000000000"
      }
    ],
    "date_written": [],
    "Format (Höhe x Breite / Anzahl folios)": null,
    "library_abb": [
      {
        "id": 1,
        "value": "ÖNB"
      }
    ]
  },
  "17": {
    "id": 17,
    "order": "17.00000000000000000000",
    "name": [
      {
        "id": 8,
        "value": "Cambr. St.John's Coll., MS 127"
      }
    ],
    "jad_id": "jad_manuscript__17",
    "library": [
      {
        "id": 8,
        "value": "St John's College (Cambridge)",
        "order": "8.00000000000000000000"
      }
    ],
    "idno": "MS 127",
    "catalog_url": "",
    "digi_url": "",
    "institutional_context": [],
    "date_written": [
      {
        "id": 43,
        "value": "14th cen.",
        "order": "43.00000000000000000000"
      }
    ],
    "Format (Höhe x Breite / Anzahl folios)": null,
    "library_abb": [
      {
        "id": 8,
        "value": "Cambr. St.John's Coll."
      }
    ]
  },
  "18": {
    "id": 18,
    "order": "18.00000000000000000000",
    "name": [
      {
        "id": 2,
        "value": "BNF, Latin 3829"
      }
    ],
    "jad_id": "jad_manuscript__18",
    "library": [
      {
        "id": 2,
        "value": "Bibliothèque Nationale de France",
        "order": "2.00000000000000000000"
      }
    ],
    "idno": "Latin 3829",
    "catalog_url": "https://archivesetmanuscrits.bnf.fr/ark:/12148/cc61794x",
    "digi_url": "https://gallica.bnf.fr/ark:/12148/btv1b9068440b/f133.item",
    "institutional_context": [],
    "date_written": [
      {
        "id": 5,
        "value": "late 12th cen.",
        "order": "5.00000000000000000000"
      }
    ],
    "Format (Höhe x Breite / Anzahl folios)": "24 x 16, 189 ff.",
    "library_abb": [
      {
        "id": 2,
        "value": "BNF"
      }
    ]
  },
  "19": {
    "id": 19,
    "order": "19.00000000000000000000",
    "name": [
      {
        "id": 2,
        "value": "BNF, Latin 3567"
      }
    ],
    "jad_id": "jad_manuscript__19",
    "library": [
      {
        "id": 2,
        "value": "Bibliothèque Nationale de France",
        "order": "2.00000000000000000000"
      }
    ],
    "idno": "Latin 3567",
    "catalog_url": "https://archivesetmanuscrits.bnf.fr/ark:/12148/cc61499m",
    "digi_url": "https://gallica.bnf.fr/ark:/12148/btv1b52521779w/f70.item",
    "institutional_context": [],
    "date_written": [],
    "Format (Höhe x Breite / Anzahl folios)": null,
    "library_abb": [
      {
        "id": 2,
        "value": "BNF"
      }
    ]
  },
  "20": {
    "id": 20,
    "order": "20.00000000000000000000",
    "name": [
      {
        "id": 2,
        "value": "BNF, Latin 3570"
      }
    ],
    "jad_id": "jad_manuscript__20",
    "library": [
      {
        "id": 2,
        "value": "Bibliothèque Nationale de France",
        "order": "2.00000000000000000000"
      }
    ],
    "idno": "Latin 3570",
    "catalog_url": "https://archivesetmanuscrits.bnf.fr/ark:/12148/cc61503g",
    "digi_url": "https://gallica.bnf.fr/ark:/12148/btv1b10024830x/f171.item",
    "institutional_context": [
      {
        "id": 12,
        "value": "St. Victor Paris",
        "order": "12.00000000000000000000"
      }
    ],
    "date_written": [
      {
        "id": 41,
        "value": "13th cen.",
        "order": "41.00000000000000000000"
      }
    ],
    "Format (Höhe x Breite / Anzahl folios)": null,
    "library_abb": [
      {
        "id": 2,
        "value": "BNF"
      }
    ]
  },
  "21": {
    "id": 21,
    "order": "21.00000000000000000000",
    "name": [
      {
        "id": 2,
        "value": "BNF, Latin 3281"
      }
    ],
    "jad_id": "jad_manuscript__21",
    "library": [
      {
        "id": 2,
        "value": "Bibliothèque Nationale de France",
        "order": "2.00000000000000000000"
      }
    ],
    "idno": "Latin 3281",
    "catalog_url": "https://archivesetmanuscrits.bnf.fr/ark:/12148/cc61156j",
    "digi_url": "",
    "institutional_context": [
      {
        "id": 1,
        "value": "University of Paris",
        "order": "1.00000000000000000000"
      }
    ],
    "date_written": [
      {
        "id": 21,
        "value": "mid 13th cen.",
        "order": "21.00000000000000000000"
      }
    ],
    "Format (Höhe x Breite / Anzahl folios)": "34 x 23, 347 ff.",
    "library_abb": [
      {
        "id": 2,
        "value": "BNF"
      }
    ]
  },
  "22": {
    "id": 22,
    "order": "22.00000000000000000000",
    "name": [
      {
        "id": 9,
        "value": "Troyes, MS 653"
      }
    ],
    "jad_id": "jad_manuscript__22",
    "library": [
      {
        "id": 9,
        "value": "Bibliothèque municipale (Troyes)",
        "order": "9.00000000000000000000"
      }
    ],
    "idno": "MS 653",
    "catalog_url": "https://arca.irht.cnrs.fr/ark:/63955/md82k643c86h",
    "digi_url": "https://arca.irht.cnrs.fr/ark:/63955/md82k643c86h",
    "institutional_context": [],
    "date_written": [],
    "Format (Höhe x Breite / Anzahl folios)": null,
    "library_abb": [
      {
        "id": 9,
        "value": "Troyes"
      }
    ]
  },
  "23": {
    "id": 23,
    "order": "23.00000000000000000000",
    "name": [
      {
        "id": 5,
        "value": "Maz., MS 178"
      }
    ],
    "jad_id": "jad_manuscript__23",
    "library": [
      {
        "id": 5,
        "value": "Bibliothèque Mazarine",
        "order": "5.00000000000000000000"
      }
    ],
    "idno": "MS 178",
    "catalog_url": "https://calames.abes.fr/pub/mazarine.aspx#details?id=MAZA10336",
    "digi_url": "",
    "institutional_context": [
      {
        "id": 1,
        "value": "University of Paris",
        "order": "1.00000000000000000000"
      }
    ],
    "date_written": [
      {
        "id": 20,
        "value": "early 13th cen.",
        "order": "20.00000000000000000000"
      }
    ],
    "Format (Höhe x Breite / Anzahl folios)": "32 x 23, 231 ff.",
    "library_abb": [
      {
        "id": 5,
        "value": "Maz."
      }
    ]
  },
  "24": {
    "id": 24,
    "order": "24.00000000000000000000",
    "name": [
      {
        "id": 5,
        "value": "Maz., MS 999"
      }
    ],
    "jad_id": "jad_manuscript__24",
    "library": [
      {
        "id": 5,
        "value": "Bibliothèque Mazarine",
        "order": "5.00000000000000000000"
      }
    ],
    "idno": "MS 999",
    "catalog_url": "https://calames.abes.fr/pub/mazarine.aspx#details?id=MAZA14392",
    "digi_url": "",
    "institutional_context": [
      {
        "id": 1,
        "value": "University of Paris",
        "order": "1.00000000000000000000"
      }
    ],
    "date_written": [
      {
        "id": 41,
        "value": "13th cen.",
        "order": "41.00000000000000000000"
      }
    ],
    "Format (Höhe x Breite / Anzahl folios)": "21 x 13, 154 ff.",
    "library_abb": [
      {
        "id": 5,
        "value": "Maz."
      }
    ]
  },
  "25": {
    "id": 25,
    "order": "25.00000000000000000000",
    "name": [
      {
        "id": 2,
        "value": "BNF, Latin 3301C"
      }
    ],
    "jad_id": "jad_manuscript__25",
    "library": [
      {
        "id": 2,
        "value": "Bibliothèque Nationale de France",
        "order": "2.00000000000000000000"
      }
    ],
    "idno": "Latin 3301C",
    "catalog_url": "https://archivesetmanuscrits.bnf.fr/ark:/12148/cc61183f",
    "digi_url": "",
    "institutional_context": [
      {
        "id": 1,
        "value": "University of Paris",
        "order": "1.00000000000000000000"
      }
    ],
    "date_written": [
      {
        "id": 5,
        "value": "late 12th cen.",
        "order": "5.00000000000000000000"
      }
    ],
    "Format (Höhe x Breite / Anzahl folios)": "28 x 21, 121 ff.",
    "library_abb": [
      {
        "id": 2,
        "value": "BNF"
      }
    ]
  },
  "26": {
    "id": 26,
    "order": "26.00000000000000000000",
    "name": [
      {
        "id": 2,
        "value": "BNF, Latin 3733"
      }
    ],
    "jad_id": "jad_manuscript__26",
    "library": [
      {
        "id": 2,
        "value": "Bibliothèque Nationale de France",
        "order": "2.00000000000000000000"
      }
    ],
    "idno": "Latin 3733",
    "catalog_url": "https://archivesetmanuscrits.bnf.fr/ark:/12148/cc61685s",
    "digi_url": "",
    "institutional_context": [],
    "date_written": [
      {
        "id": 41,
        "value": "13th cen.",
        "order": "41.00000000000000000000"
      }
    ],
    "Format (Höhe x Breite / Anzahl folios)": "16 x 11, 186 ff.",
    "library_abb": [
      {
        "id": 2,
        "value": "BNF"
      }
    ]
  },
  "27": {
    "id": 27,
    "order": "27.00000000000000000000",
    "name": [
      {
        "id": 5,
        "value": "Maz., MS 774"
      }
    ],
    "jad_id": "jad_manuscript__27",
    "library": [
      {
        "id": 5,
        "value": "Bibliothèque Mazarine",
        "order": "5.00000000000000000000"
      }
    ],
    "idno": "MS 774",
    "catalog_url": "https://calames.abes.fr/pub/mazarine.aspx#details?id=MAZA13427",
    "digi_url": "",
    "institutional_context": [],
    "date_written": [
      {
        "id": 41,
        "value": "13th cen.",
        "order": "41.00000000000000000000"
      }
    ],
    "Format (Höhe x Breite / Anzahl folios)": null,
    "library_abb": [
      {
        "id": 5,
        "value": "Maz."
      }
    ]
  },
  "28": {
    "id": 28,
    "order": "28.00000000000000000000",
    "name": [
      {
        "id": 5,
        "value": "Maz., Ms 1026"
      }
    ],
    "jad_id": "jad_manuscript__28",
    "library": [
      {
        "id": 5,
        "value": "Bibliothèque Mazarine",
        "order": "5.00000000000000000000"
      }
    ],
    "idno": "Ms 1026",
    "catalog_url": "https://calames.abes.fr/pub/mazarine.aspx#details?id=MAZA14477",
    "digi_url": "",
    "institutional_context": [],
    "date_written": [],
    "Format (Höhe x Breite / Anzahl folios)": null,
    "library_abb": [
      {
        "id": 5,
        "value": "Maz."
      }
    ]
  },
  "29": {
    "id": 29,
    "order": "29.00000000000000000000",
    "name": [
      {
        "id": 2,
        "value": "BNF, Latin 3728"
      }
    ],
    "jad_id": "jad_manuscript__29",
    "library": [
      {
        "id": 2,
        "value": "Bibliothèque Nationale de France",
        "order": "2.00000000000000000000"
      }
    ],
    "idno": "Latin 3728",
    "catalog_url": "https://archivesetmanuscrits.bnf.fr/ark:/12148/cc61679j",
    "digi_url": "https://gallica.bnf.fr/ark:/12148/btv1b53200095q",
    "institutional_context": [],
    "date_written": [
      {
        "id": 17,
        "value": "around 1300",
        "order": "17.00000000000000000000"
      }
    ],
    "Format (Höhe x Breite / Anzahl folios)": null,
    "library_abb": [
      {
        "id": 2,
        "value": "BNF"
      }
    ]
  },
  "30": {
    "id": 30,
    "order": "30.00000000000000000000",
    "name": [
      {
        "id": 2,
        "value": "BNF, Latin 14937"
      }
    ],
    "jad_id": "jad_manuscript__30",
    "library": [
      {
        "id": 2,
        "value": "Bibliothèque Nationale de France",
        "order": "2.00000000000000000000"
      }
    ],
    "idno": "Latin 14937",
    "catalog_url": "https://archivesetmanuscrits.bnf.fr/ark:/12148/cc756668",
    "digi_url": "https://gallica.bnf.fr/ark:/12148/btv1b52508765g",
    "institutional_context": [
      {
        "id": 1,
        "value": "University of Paris",
        "order": "1.00000000000000000000"
      }
    ],
    "date_written": [],
    "Format (Höhe x Breite / Anzahl folios)": null,
    "library_abb": [
      {
        "id": 2,
        "value": "BNF"
      }
    ]
  },
  "31": {
    "id": 31,
    "order": "31.00000000000000000000",
    "name": [
      {
        "id": 2,
        "value": "BNF, Latin 2950"
      }
    ],
    "jad_id": "jad_manuscript__31",
    "library": [
      {
        "id": 2,
        "value": "Bibliothèque Nationale de France",
        "order": "2.00000000000000000000"
      }
    ],
    "idno": "Latin 2950",
    "catalog_url": "https://archivesetmanuscrits.bnf.fr/ark:/12148/cc60770d",
    "digi_url": "",
    "institutional_context": [
      {
        "id": 1,
        "value": "University of Paris",
        "order": "1.00000000000000000000"
      }
    ],
    "date_written": [],
    "Format (Höhe x Breite / Anzahl folios)": null,
    "library_abb": [
      {
        "id": 2,
        "value": "BNF"
      }
    ]
  },
  "32": {
    "id": 32,
    "order": "32.00000000000000000000",
    "name": [
      {
        "id": 13,
        "value": "Arsenal, MS 44"
      }
    ],
    "jad_id": "jad_manuscript__32",
    "library": [
      {
        "id": 13,
        "value": "Bibliothèque de l'Arsenal",
        "order": "13.00000000000000000000"
      }
    ],
    "idno": "MS 44",
    "catalog_url": "https://archivesetmanuscrits.bnf.fr/ark:/12148/cc79628g",
    "digi_url": "",
    "institutional_context": [],
    "date_written": [],
    "Format (Höhe x Breite / Anzahl folios)": null,
    "library_abb": [
      {
        "id": 13,
        "value": "Arsenal"
      }
    ]
  },
  "33": {
    "id": 33,
    "order": "33.00000000000000000000",
    "name": [
      {
        "id": 13,
        "value": "Arsenal, MS 400"
      }
    ],
    "jad_id": "jad_manuscript__33",
    "library": [
      {
        "id": 13,
        "value": "Bibliothèque de l'Arsenal",
        "order": "13.00000000000000000000"
      }
    ],
    "idno": "MS 400",
    "catalog_url": "https://archivesetmanuscrits.bnf.fr/ark:/12148/cc79585t",
    "digi_url": "",
    "institutional_context": [],
    "date_written": [
      {
        "id": 41,
        "value": "13th cen.",
        "order": "41.00000000000000000000"
      }
    ],
    "Format (Höhe x Breite / Anzahl folios)": "21 x 14, 236 ff.",
    "library_abb": [
      {
        "id": 13,
        "value": "Arsenal"
      }
    ]
  },
  "34": {
    "id": 34,
    "order": "34.00000000000000000000",
    "name": [
      {
        "id": 5,
        "value": "Maz., MS 698"
      }
    ],
    "jad_id": "jad_manuscript__34",
    "library": [
      {
        "id": 5,
        "value": "Bibliothèque Mazarine",
        "order": "5.00000000000000000000"
      }
    ],
    "idno": "MS 698",
    "catalog_url": "https://calames.abes.fr/pub/mazarine.aspx#details?id=MAZA12964",
    "digi_url": "",
    "institutional_context": [
      {
        "id": 2,
        "value": "Benedictines Auxerre",
        "order": "2.00000000000000000000"
      }
    ],
    "date_written": [
      {
        "id": 19,
        "value": "around 900",
        "order": "19.00000000000000000000"
      }
    ],
    "Format (Höhe x Breite / Anzahl folios)": "32 x 25, 157 ff.",
    "library_abb": [
      {
        "id": 5,
        "value": "Maz."
      }
    ]
  },
  "35": {
    "id": 35,
    "order": "35.00000000000000000000",
    "name": [
      {
        "id": 5,
        "value": "Maz., MS 1001"
      }
    ],
    "jad_id": "jad_manuscript__35",
    "library": [
      {
        "id": 5,
        "value": "Bibliothèque Mazarine",
        "order": "5.00000000000000000000"
      }
    ],
    "idno": "MS 1001",
    "catalog_url": "https://calames.abes.fr/pub/mazarine.aspx#details?id=MAZA14397",
    "digi_url": "",
    "institutional_context": [],
    "date_written": [],
    "Format (Höhe x Breite / Anzahl folios)": null,
    "library_abb": [
      {
        "id": 5,
        "value": "Maz."
      }
    ]
  },
  "36": {
    "id": 36,
    "order": "36.00000000000000000000",
    "name": [
      {
        "id": 15,
        "value": "Valenciennes, MS 227"
      }
    ],
    "jad_id": "jad_manuscript__36",
    "library": [
      {
        "id": 15,
        "value": "Bibliothèque municipale (Valenciennes)",
        "order": "15.00000000000000000000"
      }
    ],
    "idno": "MS 227",
    "catalog_url": "https://arca.irht.cnrs.fr/ark:/63955/md859c67z259",
    "digi_url": "",
    "institutional_context": [],
    "date_written": [],
    "Format (Höhe x Breite / Anzahl folios)": null,
    "library_abb": [
      {
        "id": 15,
        "value": "Valenciennes"
      }
    ]
  },
  "37": {
    "id": 37,
    "order": "37.00000000000000000000",
    "name": [
      {
        "id": 12,
        "value": "BSB, Clm 3721"
      }
    ],
    "jad_id": "jad_manuscript__37",
    "library": [
      {
        "id": 12,
        "value": "Bayrische Staatsbibliothek",
        "order": "12.00000000000000000000"
      }
    ],
    "idno": "Clm 3721",
    "catalog_url": "https://opacplus.bsb-muenchen.de/discovery/fulldisplay?docid=alma991037622269707356&context=L&vid=49BVB_BSB:VU1&lang=de&search_scope=MyInstitution&adaptor=Local%20Search%20Engine&tab=LibraryCatalog&query=any,contains,clm%203721&offset=0",
    "digi_url": "https://www.digitale-sammlungen.de/de/view/bsb00114266?page=,1",
    "institutional_context": [],
    "date_written": [],
    "Format (Höhe x Breite / Anzahl folios)": null,
    "library_abb": [
      {
        "id": 12,
        "value": "BSB"
      }
    ]
  },
  "38": {
    "id": 38,
    "order": "38.00000000000000000000",
    "name": [
      {
        "id": 16,
        "value": "Jena, UB, El. f. 32"
      }
    ],
    "jad_id": "jad_manuscript__38",
    "library": [
      {
        "id": 16,
        "value": "Thüringer Universitäts- und Landesbibliothek Jena",
        "order": "16.00000000000000000000"
      }
    ],
    "idno": "El. f. 32",
    "catalog_url": "https://handschriftenportal.de/search?q=settlement-search%3D%3D%27jena%27%3BFIELD-GROUP-ALL%3D%3D%2732%27&hl=true&isExtended=true",
    "digi_url": "https://handschriftenportal.de/search?q=settlement-search%3D%3D%27jena%27%3BFIELD-GROUP-ALL%3D%3D%2732%27&hl=true&isExtended=true",
    "institutional_context": [],
    "date_written": [],
    "Format (Höhe x Breite / Anzahl folios)": null,
    "library_abb": [
      {
        "id": 16,
        "value": "Jena, UB"
      }
    ]
  },
  "39": {
    "id": 39,
    "order": "39.00000000000000000000",
    "name": [
      {
        "id": 17,
        "value": "Erlangen, UB, 63/1"
      }
    ],
    "jad_id": "jad_manuscript__39",
    "library": [
      {
        "id": 17,
        "value": "Universitätsbibliothek Erlangen-Nürnberg",
        "order": "17.00000000000000000000"
      }
    ],
    "idno": "63/1",
    "catalog_url": "https://bvbat01.bib-bvb.de/TP61/start.do?Query=1035%3D%22BV045480740%22+IN+%5B1%5D&Language=De",
    "digi_url": "http://digital.bib-bvb.de/view/bvb_mets/viewer.0.6.5.jsp?folder_id=0&dvs=1736437021266~348&pid=17109356&locale=de&usePid1=true&usePid2=true",
    "institutional_context": [],
    "date_written": [],
    "Format (Höhe x Breite / Anzahl folios)": null,
    "library_abb": [
      {
        "id": 17,
        "value": "Erlangen, UB"
      }
    ]
  },
  "40": {
    "id": 40,
    "order": "40.00000000000000000000",
    "name": [
      {
        "id": 17,
        "value": "Erlangen, UB, 63/2"
      }
    ],
    "jad_id": "jad_manuscript__40",
    "library": [
      {
        "id": 17,
        "value": "Universitätsbibliothek Erlangen-Nürnberg",
        "order": "17.00000000000000000000"
      }
    ],
    "idno": "63/2",
    "catalog_url": "https://bvbat01.bib-bvb.de/TP61/start.do?Query=1035%3D%22BV045480740%22+IN+%5B1%5D&Language=De",
    "digi_url": "http://digital.bib-bvb.de/view/bvb_mets/viewer.0.6.5.jsp?folder_id=0&dvs=1736437030858~486&pid=17110225&locale=de&usePid1=true&usePid2=true",
    "institutional_context": [],
    "date_written": [],
    "Format (Höhe x Breite / Anzahl folios)": null,
    "library_abb": [
      {
        "id": 17,
        "value": "Erlangen, UB"
      }
    ]
  },
  "41": {
    "id": 41,
    "order": "41.00000000000000000000",
    "name": [
      {
        "id": 18,
        "value": "Göttweig, MS 149"
      }
    ],
    "jad_id": "jad_manuscript__41",
    "library": [
      {
        "id": 18,
        "value": "Stift Göttweig",
        "order": "18.00000000000000000000"
      }
    ],
    "idno": "MS 149",
    "catalog_url": "https://manuscripta.at/hs_detail.php?ID=36861",
    "digi_url": "",
    "institutional_context": [],
    "date_written": [],
    "Format (Höhe x Breite / Anzahl folios)": null,
    "library_abb": [
      {
        "id": 18,
        "value": "Göttweig"
      }
    ]
  },
  "42": {
    "id": 42,
    "order": "42.00000000000000000000",
    "name": [
      {
        "id": 10,
        "value": "Bodl., Laud Misc. 88"
      }
    ],
    "jad_id": "jad_manuscript__42",
    "library": [
      {
        "id": 10,
        "value": "Bodleian Library",
        "order": "10.00000000000000000000"
      }
    ],
    "idno": "Laud Misc. 88",
    "catalog_url": "https://medieval.bodleian.ox.ac.uk/catalog/manuscript_7549",
    "digi_url": "https://digital.bodleian.ox.ac.uk/objects/7340fd81-5245-4368-b859-e39a2715a73a/surfaces/f7e86b2b-e840-45a8-bfdf-1abc2bb05173/",
    "institutional_context": [
      {
        "id": 9,
        "value": "Cistercians",
        "order": "9.00000000000000000000"
      }
    ],
    "date_written": [
      {
        "id": 20,
        "value": "early 13th cen.",
        "order": "20.00000000000000000000"
      }
    ],
    "Format (Höhe x Breite / Anzahl folios)": null,
    "library_abb": [
      {
        "id": 10,
        "value": "Bodl."
      }
    ]
  },
  "43": {
    "id": 43,
    "order": "43.00000000000000000000",
    "name": [
      {
        "id": 1,
        "value": "ÖNB, MS 363"
      }
    ],
    "jad_id": "jad_manuscript__43",
    "library": [
      {
        "id": 1,
        "value": "Österreichische Nationalbibliothek",
        "order": "1.00000000000000000000"
      }
    ],
    "idno": "MS 363",
    "catalog_url": "https://search.onb.ac.at/primo-explore/fulldisplay?docid=ONB_alma71305469120003338&context=L&vid=ONB&lang=de_DE&search_scope=ONB_gesamtbestand&adaptor=Local%20Search%20Engine&tab=default_tab&query=any,contains,cod%20363%20comestor&mode=basic",
    "digi_url": "",
    "institutional_context": [
      {
        "id": 20,
        "value": "Benedictines Mondsee",
        "order": "20.00000000000000000000"
      }
    ],
    "date_written": [
      {
        "id": 5,
        "value": "late 12th cen.",
        "order": "5.00000000000000000000"
      }
    ],
    "Format (Höhe x Breite / Anzahl folios)": null,
    "library_abb": [
      {
        "id": 1,
        "value": "ÖNB"
      }
    ]
  },
  "44": {
    "id": 44,
    "order": "44.00000000000000000000",
    "name": [
      {
        "id": 19,
        "value": "Frankfurt, Barth. 56"
      }
    ],
    "jad_id": "jad_manuscript__44",
    "library": [
      {
        "id": 19,
        "value": "Frankfurt, Universitatsbibliothek",
        "order": "19.00000000000000000000"
      }
    ],
    "idno": "Barth. 56",
    "catalog_url": "https://handschriftenportal.de/search?hspobjectid=HSP-0f187f83-39a9-3335-9bd8-3632c2be9b08&q=frankfurt+56&hl=true",
    "digi_url": "",
    "institutional_context": [],
    "date_written": [
      {
        "id": 20,
        "value": "early 13th cen.",
        "order": "20.00000000000000000000"
      }
    ],
    "Format (Höhe x Breite / Anzahl folios)": null,
    "library_abb": [
      {
        "id": 19,
        "value": "Frankfurt"
      }
    ]
  },
  "45": {
    "id": 45,
    "order": "45.00000000000000000000",
    "name": [
      {
        "id": 20,
        "value": "Sankt-Florian, MS XI 216"
      }
    ],
    "jad_id": "jad_manuscript__45",
    "library": [
      {
        "id": 20,
        "value": "Sankt-Florian, Stiftsbibliothek",
        "order": "20.00000000000000000000"
      }
    ],
    "idno": "MS XI 216",
    "catalog_url": "http://18.235.151.129/detail.php?msid=24431",
    "digi_url": "",
    "institutional_context": [],
    "date_written": [],
    "Format (Höhe x Breite / Anzahl folios)": null,
    "library_abb": [
      {
        "id": 20,
        "value": "Sankt-Florian"
      }
    ]
  },
  "46": {
    "id": 46,
    "order": "46.00000000000000000000",
    "name": [
      {
        "id": 21,
        "value": "Linz, MS 488"
      }
    ],
    "jad_id": "jad_manuscript__46",
    "library": [
      {
        "id": 21,
        "value": "Linz, Oberösterreichische Landesbibliothek",
        "order": "21.00000000000000000000"
      }
    ],
    "idno": "MS 488",
    "catalog_url": "https://manuscripta.at/hs_detail.php?ID=34019",
    "digi_url": "https://digi.landesbibliothek.at/viewer/image/488/1/LOG_0001/",
    "institutional_context": [],
    "date_written": [],
    "Format (Höhe x Breite / Anzahl folios)": null,
    "library_abb": [
      {
        "id": 21,
        "value": "Linz"
      }
    ]
  },
  "47": {
    "id": 47,
    "order": "47.00000000000000000000",
    "name": [
      {
        "id": 22,
        "value": "Hamburg, Jacobi 21"
      }
    ],
    "jad_id": "jad_manuscript__47",
    "library": [
      {
        "id": 22,
        "value": "Hamburg, Stadt- und Universitatsbibliothek",
        "order": "22.00000000000000000000"
      }
    ],
    "idno": "Jacobi 21",
    "catalog_url": "",
    "digi_url": "",
    "institutional_context": [],
    "date_written": [
      {
        "id": 22,
        "value": "late 13th cen.",
        "order": "22.00000000000000000000"
      }
    ],
    "Format (Höhe x Breite / Anzahl folios)": null,
    "library_abb": [
      {
        "id": 22,
        "value": "Hamburg"
      }
    ]
  },
  "48": {
    "id": 48,
    "order": "48.00000000000000000000",
    "name": [
      {
        "id": 10,
        "value": "Bodl., Hatton 37"
      }
    ],
    "jad_id": "jad_manuscript__48",
    "library": [
      {
        "id": 10,
        "value": "Bodleian Library",
        "order": "10.00000000000000000000"
      }
    ],
    "idno": "Hatton 37",
    "catalog_url": "https://medieval.bodleian.ox.ac.uk/catalog/manuscript_6062",
    "digi_url": "",
    "institutional_context": [],
    "date_written": [
      {
        "id": 41,
        "value": "13th cen.",
        "order": "41.00000000000000000000"
      }
    ],
    "Format (Höhe x Breite / Anzahl folios)": null,
    "library_abb": [
      {
        "id": 10,
        "value": "Bodl."
      }
    ]
  },
  "49": {
    "id": 49,
    "order": "49.00000000000000000000",
    "name": [
      {
        "id": 23,
        "value": "Trinity Coll., B.14.43"
      }
    ],
    "jad_id": "jad_manuscript__49",
    "library": [
      {
        "id": 23,
        "value": "Trinity College",
        "order": "23.00000000000000000000"
      }
    ],
    "idno": "B.14.43",
    "catalog_url": "https://mss-cat.trin.cam.ac.uk/Manuscript/B.14.43",
    "digi_url": "https://mss-cat.trin.cam.ac.uk/Manuscript/B.14.43/UV#?c=0&m=0&s=0&cv=19&r=0&xywh=-786%2C-160%2C4403%2C2416",
    "institutional_context": [],
    "date_written": [
      {
        "id": 41,
        "value": "13th cen.",
        "order": "41.00000000000000000000"
      }
    ],
    "Format (Höhe x Breite / Anzahl folios)": null,
    "library_abb": [
      {
        "id": 23,
        "value": "Trinity Coll."
      }
    ]
  },
  "50": {
    "id": 50,
    "order": "50.00000000000000000000",
    "name": [
      {
        "id": 6,
        "value": "Lam., MS 71"
      }
    ],
    "jad_id": "jad_manuscript__50",
    "library": [
      {
        "id": 6,
        "value": "Lambeth Palace Library",
        "order": "6.00000000000000000000"
      }
    ],
    "idno": "MS 71",
    "catalog_url": "https://archives.lambethpalacelibrary.org.uk/CalmView/Record.aspx?src=CalmView.Catalog&id=MSS%2f71&pos=1",
    "digi_url": "",
    "institutional_context": [],
    "date_written": [
      {
        "id": 41,
        "value": "13th cen.",
        "order": "41.00000000000000000000"
      }
    ],
    "Format (Höhe x Breite / Anzahl folios)": null,
    "library_abb": [
      {
        "id": 6,
        "value": "Lam."
      }
    ]
  }
}